{
    "url": "http://some.domen",

    "loadUser": {
        "headers": {},
        "route": "/api/users/{SID}",

        "ConnectTimeout": 20,
        "Timeout": 10,
        "FollowLocation": false,

        "responseCode": 200,
        "responseData": "data"
    },

    "updateUser": {
        "headers": {},
        "method": "PUT",
        "route": "/api/users/{SID}/update",

        "ConnectTimeout": 20,
        "Timeout": 10,
        "FollowLocation": false,

        "responseCode": 200,
        "responseData": ""
    }
}